taisim/__init__.py
taisim/external_data.py
taisim/player.py
taisim/sensor.py
taisim/simulator.py
taisim/utils.py
taisim/components/__init__.py
taisim/components/log.py
taisim/components/video.py
taisim/data/Cropps1.png
taisim/data/Cropps2.png
taisim/data/LaneKeeper1.png
taisim/data/LaneKeeper2.png
taisim/data/LaneKeeper3.png
taisim/data/LineFollower1.png
taisim/data/LineFollower2.png
taisim/data/compass.png
taisim/data/logo.png
taisim/data/player.png
taisim/data/position.png
taisim/data/taisim.png
taisim/data/taisim_logo.png
taisim/gui/__init__.py
taisim/gui/help_bar.py
taisim/gui/sensor_bar.py
taisim-0.1.1.dist-info/LICENSE
taisim-0.1.1.dist-info/METADATA
taisim-0.1.1.dist-info/WHEEL
taisim-0.1.1.dist-info/entry_points.txt
taisim-0.1.1.dist-info/top_level.txt
taisim-0.1.1.dist-info/RECORD
